esparpy/__init__.py
esparpy/common.py
esparpy/esparpy.py
esparpy-0.0.1.dist-info/LICENSE
esparpy-0.0.1.dist-info/METADATA
esparpy-0.0.1.dist-info/WHEEL
esparpy-0.0.1.dist-info/entry_points.txt
esparpy-0.0.1.dist-info/top_level.txt
esparpy-0.0.1.dist-info/RECORD
